crashplancli/__init__.py
crashplancli/__main__.py
crashplancli/bulk.py
crashplancli/config.py
crashplancli/date_helper.py
crashplancli/enums.py
crashplancli/errors.py
crashplancli/file_readers.py
crashplancli/main.py
crashplancli/options.py
crashplancli/output_formats.py
crashplancli/password.py
crashplancli/profile.py
crashplancli/sdk_client.py
crashplancli/util.py
crashplancli/worker.py
crashplancli/click_ext/__init__.py
crashplancli/click_ext/groups.py
crashplancli/click_ext/options.py
crashplancli/click_ext/types.py
crashplancli/cmds/__init__.py
crashplancli/cmds/auditlogs.py
crashplancli/cmds/devices.py
crashplancli/cmds/legal_hold.py
crashplancli/cmds/profile.py
crashplancli/cmds/shared.py
crashplancli/cmds/shell.py
crashplancli/cmds/users.py
crashplancli/cmds/util.py
crashplancli/cmds/search/__init__.py
crashplancli/cmds/search/cursor_store.py
crashplancli/cmds/search/options.py
crashplancli/extensions/__init__.py
crashplancli/logger/__init__.py
crashplancli/logger/enums.py
crashplancli/logger/handlers.py
crashplancli-1.0.2.dist-info/licenses/LICENSE.md
crashplancli-1.0.2.dist-info/METADATA
crashplancli-1.0.2.dist-info/WHEEL
crashplancli-1.0.2.dist-info/entry_points.txt
crashplancli-1.0.2.dist-info/top_level.txt
crashplancli-1.0.2.dist-info/RECORD
