Metadata-Version: 2.4
Name: crashplancli
Version: 1.0.2
Summary: The official command line tool for interacting with CrashPlan
License-Expression: MIT
Project-URL: Homepage, https://github.com/CrashPlan-Labs
Project-URL: Issues, https://github.com/CrashPlan-Labs/crashplancli/issues
Project-URL: Documentation, https://crashplanclidocs.crashplan.com/
Project-URL: Repository, https://github.com/CrashPlan-Labs/crashplancli
Keywords: backup,crashplan
Classifier: Development Status :: 5 - Production/Stable
Classifier: Natural Language :: English
Classifier: Intended Audience :: Developers
Classifier: Programming Language :: Python :: 3
Classifier: Programming Language :: Python :: 3.11
Classifier: Programming Language :: Python :: 3.12
Classifier: Programming Language :: Python :: 3.13
Classifier: Programming Language :: Python :: Implementation :: CPython
Requires-Python: <4,>=3.11
License-File: LICENSE.md
Requires-Dist: chardet
Requires-Dist: click>=8.1.8
Requires-Dist: click_plugins>=1.1.1
Requires-Dist: colorama>=0.4.6
Requires-Dist: keyring==25.6.0
Requires-Dist: keyrings.alt==5.0.2
Requires-Dist: ipython>=8.10.0; python_version >= "3.11"
Requires-Dist: pandas>=2.2.3
Requires-Dist: pycpg>=1.0.4
Requires-Dist: setuptools>=66.0.0
Provides-Extra: docs
Requires-Dist: sphinx==8.2.3; extra == "docs"
Requires-Dist: myst-parser==4.0.1; extra == "docs"
Requires-Dist: sphinx_rtd_theme==3.0.2; extra == "docs"
Requires-Dist: docutils==0.21.2; extra == "docs"
Requires-Dist: sphinx-click==6.0.0; extra == "docs"
Provides-Extra: dev
Requires-Dist: flake8==4.0.0; extra == "dev"
Requires-Dist: pytest==8.3.5; extra == "dev"
Requires-Dist: pytest-cov==4.0.0; extra == "dev"
Requires-Dist: pytest-mock==3.10.0; extra == "dev"
Requires-Dist: tox==4.25.0; extra == "dev"
Requires-Dist: importlib-metadata<5.0; extra == "dev"
Dynamic: license-file
